MANIFEST.in
README.md
requirements.txt
setup.py
tests/test_client_config.py
tests/test_option_helper.py
tests/test_option_util.py
tests/test_push_client.py
tests/test_quote_client.py
tests/test_trade_client.py
tests/test_utils.py
tigeropen/__init__.py
tigeropen/tiger_open_client.py
tigeropen/tiger_open_config.py
tigeropen.egg-info/PKG-INFO
tigeropen.egg-info/SOURCES.txt
tigeropen.egg-info/dependency_links.txt
tigeropen.egg-info/requires.txt
tigeropen.egg-info/top_level.txt
tigeropen/common/__init__.py
tigeropen/common/exceptions.py
tigeropen/common/model.py
tigeropen/common/request.py
tigeropen/common/response.py
tigeropen/common/consts/__init__.py
tigeropen/common/consts/filter_fields.py
tigeropen/common/consts/fundamental_fields.py
tigeropen/common/consts/params.py
tigeropen/common/consts/push_destinations.py
tigeropen/common/consts/push_subscriptions.py
tigeropen/common/consts/push_types.py
tigeropen/common/consts/quote_keys.py
tigeropen/common/consts/service_types.py
tigeropen/common/consts/tick_constants.py
tigeropen/common/util/__init__.py
tigeropen/common/util/account_util.py
tigeropen/common/util/common_utils.py
tigeropen/common/util/contract_utils.py
tigeropen/common/util/order_utils.py
tigeropen/common/util/price_util.py
tigeropen/common/util/signature_utils.py
tigeropen/common/util/string_utils.py
tigeropen/common/util/tick_util.py
tigeropen/common/util/web_utils.py
tigeropen/examples/__init__.py
tigeropen/examples/client_config.py
tigeropen/examples/financial_demo.py
tigeropen/examples/nasdaq100.py
tigeropen/examples/push_client_demo.py
tigeropen/examples/push_client_stomp_demo.py
tigeropen/examples/quote_client_demo.py
tigeropen/examples/trade_client_demo.py
tigeropen/examples/option_helpers/__init__.py
tigeropen/examples/option_helpers/extra_calculator.py
tigeropen/examples/option_helpers/helpers.py
tigeropen/examples/option_helpers/probability_calculator.py
tigeropen/examples/option_helpers/util.py
tigeropen/fundamental/__init__.py
tigeropen/fundamental/domain/__init__.py
tigeropen/fundamental/request/__init__.py
tigeropen/fundamental/request/model.py
tigeropen/fundamental/response/__init__.py
