Metadata-Version: 2.4
Name: tigeropen
Version: 3.5.2
Summary: TigerBrokers Open API
Home-page: https://github.com/tigerbrokers/openapi-python-sdk
Author: TigerBrokers
Author-email: openapi@itiger.com
License: Apache License v2
Platform: any
Classifier: Programming Language :: Python
Classifier: Operating System :: Microsoft :: Windows
Classifier: Operating System :: Unix
Classifier: Programming Language :: Python :: 3.8
Classifier: Programming Language :: Python :: 3.9
Classifier: Programming Language :: Python :: 3.10
Classifier: Programming Language :: Python :: 3.11
Classifier: Programming Language :: Python :: 3.12
Classifier: Programming Language :: Python :: 3.13
Requires-Dist: simplejson
Requires-Dist: delorean
Requires-Dist: pandas
Requires-Dist: python-dateutil
Requires-Dist: pytz
Requires-Dist: pyasn1
Requires-Dist: rsa
Requires-Dist: stomp.py
Requires-Dist: getmac
Requires-Dist: cryptography~=41.0.7
Requires-Dist: backoff
Requires-Dist: jproperties
Requires-Dist: protobuf
Requires-Dist: google-cloud
Requires-Dist: urllib3
Dynamic: author
Dynamic: author-email
Dynamic: classifier
Dynamic: description
Dynamic: description-content-type
Dynamic: home-page
Dynamic: license
Dynamic: platform
Dynamic: requires-dist
Dynamic: summary
